pyloggermanager/__init__.py
pyloggermanager/__main__.py
pyloggermanager/formatters/__init__.py
pyloggermanager/formatters/__main__.py
pyloggermanager/handlers/__init__.py
pyloggermanager/handlers/__main__.py
pyloggermanager/streams/__init__.py
pyloggermanager/streams/__main__.py
pyloggermanager-0.1.4.dist-info/LICENSE
pyloggermanager-0.1.4.dist-info/METADATA
pyloggermanager-0.1.4.dist-info/WHEEL
pyloggermanager-0.1.4.dist-info/top_level.txt
pyloggermanager-0.1.4.dist-info/RECORD
