Metadata-Version: 2.1
Name: pyloggermanager
Version: 0.1.4
Summary: The pyloggermanager package is a vital logging framework for Python applications, providing developers with essential
Home-page: https://github.com/coldsofttech/pyloggermanager
Author: coldsofttech
License: MIT
Keywords: logger,logging,logging-framework,logger-manager
Classifier: Development Status :: 4 - Beta
Classifier: Intended Audience :: Developers
Classifier: Topic :: Software Development :: Libraries :: Python Modules
Classifier: Topic :: System :: Logging
Classifier: License :: OSI Approved :: MIT License
Classifier: Programming Language :: Python :: 3.10
Classifier: Programming Language :: Python :: 3.11
Classifier: Programming Language :: Python :: 3.12
License-File: LICENSE
Requires-Dist: pycolorecho
